[{
    "title": "美食定制：猝不及防吃吃",
    "icon": "../static/img/team-r3-1.png",
    "name": "小天使",
    "time": "2017-10-01",
    "like": "120",
    "comment": "46"
  },
  {
    "title": "美食定制：猝不及防吃吃",
    "icon": "../static/img/team-r3-1.png",
    "name": "小天使",
    "time": "2017-10-01",
    "like": "120",
    "comment": "46"
  }, {
    "title": "美食定制：猝不及防吃吃",
    "icon": "../static/img/team-r3-1.png",
    "name": "小天使",
    "time": "2017-10-01",
    "like": "120",
    "comment": "46"
  },
  {
    "title": "美食定制：猝不及防吃吃",
    "icon": "../static/img/team-r3-1.png",
    "name": "小天使",
    "time": "2017-10-01",
    "like": "120",
    "comment": "46"
  }
]
